{
  "Docking": {
    "Data": []
  },
  "MainWindow": {
    "GLOBAL": {
      "fps": "120",
      "height": "856",
      "maximized": "1",
      "style": "0",
      "userScale": "2",
      "width": "1512",
      "xpos": "224",
      "ypos": "133"
    }
  },
  "Window": {
    "###/FMSInfo": {
      "Collapsed": "0",
      "Pos": "60,60",
      "Size": "181,167"
    },
    "###/SmartDashboard/Auto Chooser": {
      "Collapsed": "0",
      "Pos": "1152,29",
      "Size": "254,54"
    },
    "###/SmartDashboard/Field": {
      "Collapsed": "0",
      "Pos": "239,50",
      "Size": "723,537"
    },
    "###/SmartDashboard/odo_raw": {
      "Collapsed": "0",
      "Pos": "535,-31",
      "Size": "648,609"
    },
    "###FMS": {
      "Collapsed": "0",
      "Pos": "1,652",
      "Size": "175,184"
    },
    "###Joysticks": {
      "Collapsed": "0",
      "Pos": "180,682",
      "Size": "796,155"
    },
    "###Keyboard 0 Settings": {
      "Collapsed": "0",
      "Pos": "135,77",
      "Size": "300,560"
    },
    "###NetworkTables": {
      "Collapsed": "0",
      "Pos": "982,28",
      "Size": "525,811"
    },
    "###NetworkTables Info": {
      "Collapsed": "0",
      "Pos": "232,525",
      "Size": "750,144"
    },
    "###Other Devices": {
      "Collapsed": "0",
      "Pos": "1258,110",
      "Size": "250,695"
    },
    "###Plot <0>": {
      "Collapsed": "0",
      "Pos": "229,59",
      "Size": "700,400"
    },
    "###RoboRIO": {
      "Collapsed": "0",
      "Pos": "1,503",
      "Size": "119,146"
    },
    "###System Joysticks": {
      "Collapsed": "0",
      "Pos": "3,283",
      "Size": "192,218"
    },
    "###Timing": {
      "Collapsed": "0",
      "Pos": "5,150",
      "Size": "135,127"
    },
    "Debug##Default": {
      "Collapsed": "0",
      "Pos": "60,60",
      "Size": "400,400"
    },
    "Robot State": {
      "Collapsed": "0",
      "Pos": "5,20",
      "Size": "92,116"
    }
  }
}
